simplesplit
