Metadata-Version: 2.1
Name: SimpleSplit
Version: 0.1.1
Summary: Split and re-combine large binary files
Home-page: https://github.com/fakerybakery/simplesplit
Author: GitHub @fakerybakery
Author-email: me@mrfake.name
License: UNKNOWN
Platform: Any
Classifier: Programming Language :: Python :: 3
Classifier: Operating System :: OS Independent
Requires-Python: >=3.9
